{"generated_at_utc":"2026-07-16T09:38:37+00:00","ist_date":"2026-07-16","source":"Open-Meteo Forecast API (https://open-meteo.com/)","districts":{"1":{"o":{"light":0,"moderate":0,"heavy":0,"very-high":0},"max_wbgt":24.9,"valid":24},"2":{"o":{"light":0,"moderate":0,"heavy":0,"very-high":1},"max_wbgt":26.41,"valid":24},"3":{"o":{"light":0,"moderate":0,"heavy":0,"very-high":0},"max_wbgt":15.83,"valid":24},"4":{"o":{"light":0,"moderate":0,"heavy":0,"very-high":0},"max_wbgt":17.24,"valid":24},"5":{"o":{"light":0,"moderate":0,"heavy":2,"very-high":4},"max_wbgt":28.27,"valid":24},"6":{"o":{"light":0,"moderate":3,"heavy":5,"very-high":6},"max_wbgt":31.25,"valid":24},"7":{"o":{"light":2,"moderate":5,"heavy":6,"very-high":6},"max_wbgt":31.36,"valid":24},"8":{"o":{"light":0,"moderate":1,"heavy":4,"very-high":5},"max_wbgt":29.94,"valid":24},"9":{"o":{"light":0,"moderate":0,"heavy":0,"very-high":0},"max_wbgt":20.78,"valid":24},"10":{"o":{"light":0,"moderate":0,"heavy":2,"very-high":3},"max_wbgt":30.93,"valid":24},"11":{"o":{"light":0,"moderate":0,"heavy":0,"very-high":0},"max_wbgt":19.95,"valid":24},"12":{"o":{"light":0,"moderate":0,"heavy":0,"very-high":1},"max_wbgt":27.56,"valid":24},"13":{"o":{"light":0,"moderate":1,"heavy":1,"very-high":2},"max_wbgt":28.1,"valid":24},"14":{"o":{"light":0,"moderate":0,"heavy":0,"very-high":0},"max_wbgt":26.05,"valid":24},"15":{"o":{"light":0,"moderate":0,"heavy":0,"very-high":0},"max_wbgt":22.59,"valid":24},"16":{"o":{"light":0,"moderate":2,"heavy":3,"very-high":4},"max_wbgt":29.15,"valid":24},"17":{"o":{"light":0,"moderate":3,"heavy":6,"very-high":6},"max_wbgt":30.06,"valid":24},"18":{"o":{"light":0,"moderate":0,"heavy":0,"very-high":0},"max_wbgt":22.74,"valid":24},"19":{"o":{"light":0,"moderate":0,"heavy":1,"very-high":2},"max_wbgt":27.26,"valid":24},"20":{"o":{"light":0,"moderate":4,"heavy":4,"very-high":5},"max_wbgt":32.88,"valid":24},"21":{"o":{"light":5,"moderate":6,"heavy":6,"very-high":6},"max_wbgt":33.32,"valid":24},"22":{"o":{"light":5,"moderate":6,"heavy":6,"very-high":6},"max_wbgt":33.97,"valid":24},"23":{"o":{"light":0,"moderate":0,"heavy":0,"very-high":0},"max_wbgt":24.89,"valid":24},"24":{"o":{"light":0,"moderate":4,"heavy":6,"very-high":6},"max_wbgt":30.82,"valid":24},"25":{"o":{"light":0,"moderate":0,"heavy":0,"very-high":0},"max_wbgt":14.71,"valid":24},"26":{"o":{"light":0,"moderate":0,"heavy":0,"very-high":0},"max_wbgt":19.23,"valid":24},"27":{"o":{"light":0,"moderate":0,"heavy":0,"very-high":4},"max_wbgt":27.06,"valid":24},"28":{"o":{"light":2,"moderate":6,"heavy":6,"very-high":6},"max_wbgt":31.32,"valid":24},"29":{"o":{"light":3,"moderate":6,"heavy":6,"very-high":6},"max_wbgt":32.6,"valid":24},"30":{"o":{"light":2,"moderate":6,"heavy":6,"very-high":6},"max_wbgt":32.92,"valid":24},"31":{"o":{"light":1,"moderate":4,"heavy":6,"very-high":6},"max_wbgt":32.68,"valid":24},"32":{"o":{"light":0,"moderate":0,"heavy":0,"very-high":2},"max_wbgt":26.84,"valid":24},"33":{"o":{"light":0,"moderate":0,"heavy":0,"very-high":1},"max_wbgt":25.77,"valid":24},"34":{"o":{"light":0,"moderate":0,"heavy":0,"very-high":2},"max_wbgt":25.64,"valid":24},"35":{"o":{"light":5,"moderate":6,"heavy":6,"very-high":6},"max_wbgt":34.26,"valid":24},"36":{"o":{"light":6,"moderate":6,"heavy":6,"very-high":6},"max_wbgt":35.08,"valid":24},"37":{"o":{"light":6,"moderate":6,"heavy":6,"very-high":6},"max_wbgt":34.51,"valid":24},"38":{"o":{"light":4,"moderate":6,"heavy":6,"very-high":6},"max_wbgt":33.07,"valid":24},"39":{"o":{"light":4,"moderate":6,"heavy":6,"very-high":6},"max_wbgt":32.84,"valid":24},"40":{"o":{"light":5,"moderate":6,"heavy":6,"very-high":6},"max_wbgt":32.85,"valid":24},"41":{"o":{"light":6,"moderate":6,"heavy":6,"very-high":6},"max_wbgt":33.48,"valid":24},"42":{"o":{"light":6,"moderate":6,"heavy":6,"very-high":6},"max_wbgt":34.12,"valid":24},"43":{"o":{"light":6,"moderate":6,"heavy":6,"very-high":6},"max_wbgt":33.79,"valid":24},"44":{"o":{"light":4,"moderate":6,"heavy":6,"very-high":6},"max_wbgt":33.56,"valid":24},"45":{"o":{"light":5,"moderate":6,"heavy":6,"very-high":6},"max_wbgt":33.32,"valid":24},"46":{"o":{"light":5,"moderate":6,"heavy":6,"very-high":6},"max_wbgt":33.08,"valid":24},"47":{"o":{"light":6,"moderate":6,"heavy":6,"very-high":6},"max_wbgt":32.93,"valid":24},"48":{"o":{"light":5,"moderate":6,"heavy":6,"very-high":6},"max_wbgt":32.74,"valid":24},"49":{"o":{"light":6,"moderate":6,"heavy":6,"very-high":6},"max_wbgt":34.34,"valid":24},"50":{"o":{"light":6,"moderate":6,"heavy":6,"very-high":6},"max_wbgt":34.55,"valid":24},"51":{"o":{"light":5,"moderate":6,"heavy":6,"very-high":6},"max_wbgt":33.94,"valid":24},"52":{"o":{"light":4,"moderate":6,"heavy":6,"very-high":6},"max_wbgt":32.44,"valid":24},"53":{"o":{"light":6,"moderate":6,"heavy":6,"very-high":6},"max_wbgt":32.97,"valid":24},"54":{"o":{"light":5,"moderate":6,"heavy":6,"very-high":6},"max_wbgt":33.22,"valid":24},"55":{"o":{"light":5,"moderate":6,"heavy":6,"very-high":6},"max_wbgt":32.1,"valid":24},"56":{"o":{"light":0,"moderate":0,"heavy":0,"very-high":0},"max_wbgt":12.46,"valid":24},"57":{"o":{"light":0,"moderate":1,"heavy":3,"very-high":4},"max_wbgt":28.9,"valid":24},"58":{"o":{"light":0,"moderate":1,"heavy":3,"very-high":3},"max_wbgt":29.27,"valid":24},"59":{"o":{"light":0,"moderate":1,"heavy":2,"very-high":3},"max_wbgt":29.2,"valid":24},"60":{"o":{"light":0,"moderate":4,"heavy":5,"very-high":6},"max_wbgt":29.78,"valid":24},"61":{"o":{"light":0,"moderate":3,"heavy":4,"very-high":5},"max_wbgt":28.62,"valid":24},"62":{"o":{"light":0,"moderate":0,"heavy":0,"very-high":0},"max_wbgt":12.06,"valid":24},"63":{"o":{"light":0,"moderate":0,"heavy":0,"very-high":0},"max_wbgt":31.08,"valid":24},"64":{"o":{"light":0,"moderate":3,"heavy":4,"very-high":5},"max_wbgt":29.73,"valid":24},"65":{"o":{"light":0,"moderate":1,"heavy":3,"very-high":4},"max_wbgt":28.62,"valid":24},"66":{"o":{"light":1,"moderate":5,"heavy":6,"very-high":6},"max_wbgt":32.78,"valid":24},"67":{"o":{"light":4,"moderate":6,"heavy":6,"very-high":6},"max_wbgt":35.89,"valid":24},"68":{"o":{"light":6,"moderate":6,"heavy":6,"very-high":6},"max_wbgt":35.25,"valid":24},"69":{"o":{"light":2,"moderate":6,"heavy":6,"very-high":6},"max_wbgt":30.8,"valid":24},"70":{"o":{"light":5,"moderate":6,"heavy":6,"very-high":6},"max_wbgt":32.58,"valid":24},"71":{"o":{"light":5,"moderate":6,"heavy":6,"very-high":6},"max_wbgt":33.17,"valid":24},"72":{"o":{"light":5,"moderate":6,"heavy":6,"very-high":6},"max_wbgt":32.58,"valid":24},"73":{"o":{"light":5,"moderate":6,"heavy":6,"very-high":6},"max_wbgt":32.6,"valid":24},"74":{"o":{"light":6,"moderate":6,"heavy":6,"very-high":6},"max_wbgt":32.36,"valid":24},"75":{"o":{"light":5,"moderate":6,"heavy":6,"very-high":6},"max_wbgt":32.2,"valid":24},"76":{"o":{"light":6,"moderate":6,"heavy":6,"very-high":6},"max_wbgt":32.49,"valid":24},"77":{"o":{"light":6,"moderate":6,"heavy":6,"very-high":6},"max_wbgt":32.41,"valid":24},"78":{"o":{"light":6,"moderate":6,"heavy":6,"very-high":6},"max_wbgt":32.79,"valid":24},"79":{"o":{"light":6,"moderate":6,"heavy":6,"very-high":6},"max_wbgt":32.63,"valid":24},"80":{"o":{"light":6,"moderate":6,"heavy":6,"very-high":6},"max_wbgt":32.48,"valid":24},"81":{"o":{"light":4,"moderate":6,"heavy":6,"very-high":6},"max_wbgt":32.62,"valid":24},"82":{"o":{"light":5,"moderate":6,"heavy":6,"very-high":6},"max_wbgt":32.47,"valid":24},"83":{"o":{"light":4,"moderate":6,"heavy":6,"very-high":6},"max_wbgt":32.39,"valid":24},"84":{"o":{"light":2,"moderate":6,"heavy":6,"very-high":6},"max_wbgt":32.26,"valid":24},"85":{"o":{"light":2,"moderate":6,"heavy":6,"very-high":6},"max_wbgt":32.25,"valid":24},"86":{"o":{"light":3,"moderate":6,"heavy":6,"very-high":6},"max_wbgt":32.28,"valid":24},"87":{"o":{"light":2,"moderate":6,"heavy":6,"very-high":6},"max_wbgt":32.42,"valid":24},"88":{"o":{"light":3,"moderate":6,"heavy":6,"very-high":6},"max_wbgt":32.4,"valid":24},"89":{"o":{"light":3,"moderate":6,"heavy":6,"very-high":6},"max_wbgt":32.49,"valid":24},"90":{"o":{"light":5,"moderate":6,"heavy":6,"very-high":6},"max_wbgt":32.45,"valid":24},"91":{"o":{"light":4,"moderate":6,"heavy":6,"very-high":6},"max_wbgt":32.46,"valid":24},"92":{"o":{"light":4,"moderate":6,"heavy":6,"very-high":6},"max_wbgt":32.46,"valid":24},"93":{"o":{"light":4,"moderate":6,"heavy":6,"very-high":6},"max_wbgt":32.65,"valid":24},"94":{"o":{"light":3,"moderate":6,"heavy":6,"very-high":6},"max_wbgt":32.41,"valid":24},"95":{"o":{"light":4,"moderate":6,"heavy":6,"very-high":6},"max_wbgt":32.65,"valid":24},"96":{"o":{"light":3,"moderate":6,"heavy":6,"very-high":6},"max_wbgt":32.58,"valid":24},"97":{"o":{"light":4,"moderate":6,"heavy":6,"very-high":6},"max_wbgt":32.61,"valid":24},"98":{"o":{"light":3,"moderate":6,"heavy":6,"very-high":6},"max_wbgt":32.54,"valid":24},"99":{"o":{"light":3,"moderate":6,"heavy":6,"very-high":6},"max_wbgt":33.33,"valid":24},"100":{"o":{"light":4,"moderate":6,"heavy":6,"very-high":6},"max_wbgt":33.21,"valid":24},"101":{"o":{"light":2,"moderate":6,"heavy":6,"very-high":6},"max_wbgt":32.97,"valid":24},"102":{"o":{"light":2,"moderate":6,"heavy":6,"very-high":6},"max_wbgt":32.62,"valid":24},"103":{"o":{"light":2,"moderate":6,"heavy":6,"very-high":6},"max_wbgt":31.78,"valid":24},"104":{"o":{"light":1,"moderate":5,"heavy":6,"very-high":6},"max_wbgt":32.06,"valid":24},"105":{"o":{"light":3,"moderate":6,"heavy":6,"very-high":6},"max_wbgt":32.61,"valid":24},"106":{"o":{"light":3,"moderate":6,"heavy":6,"very-high":6},"max_wbgt":32.18,"valid":24},"107":{"o":{"light":1,"moderate":5,"heavy":6,"very-high":6},"max_wbgt":32.34,"valid":24},"108":{"o":{"light":1,"moderate":6,"heavy":6,"very-high":6},"max_wbgt":31.92,"valid":24},"109":{"o":{"light":1,"moderate":6,"heavy":6,"very-high":6},"max_wbgt":32.01,"valid":24},"110":{"o":{"light":0,"moderate":5,"heavy":6,"very-high":6},"max_wbgt":31.09,"valid":24},"111":{"o":{"light":1,"moderate":5,"heavy":6,"very-high":6},"max_wbgt":31.85,"valid":24},"112":{"o":{"light":1,"moderate":5,"heavy":6,"very-high":6},"max_wbgt":31.9,"valid":24},"113":{"o":{"light":0,"moderate":5,"heavy":6,"very-high":6},"max_wbgt":31.2,"valid":24},"114":{"o":{"light":1,"moderate":6,"heavy":7,"very-high":7},"max_wbgt":31.36,"valid":24},"115":{"o":{"light":1,"moderate":6,"heavy":6,"very-high":6},"max_wbgt":31.56,"valid":24},"116":{"o":{"light":1,"moderate":6,"heavy":6,"very-high":6},"max_wbgt":31.39,"valid":24},"117":{"o":{"light":0,"moderate":4,"heavy":6,"very-high":6},"max_wbgt":31.09,"valid":24},"118":{"o":{"light":1,"moderate":5,"heavy":6,"very-high":6},"max_wbgt":31.04,"valid":24},"119":{"o":{"light":0,"moderate":3,"heavy":6,"very-high":6},"max_wbgt":30.85,"valid":24},"120":{"o":{"light":1,"moderate":5,"heavy":6,"very-high":6},"max_wbgt":31.95,"valid":24},"121":{"o":{"light":1,"moderate":5,"heavy":6,"very-high":6},"max_wbgt":32.35,"valid":24},"122":{"o":{"light":0,"moderate":4,"heavy":6,"very-high":6},"max_wbgt":31.07,"valid":24},"123":{"o":{"light":0,"moderate":1,"heavy":4,"very-high":6},"max_wbgt":29.79,"valid":24},"124":{"o":{"light":0,"moderate":6,"heavy":6,"very-high":6},"max_wbgt":31.13,"valid":24},"125":{"o":{"light":0,"moderate":4,"heavy":6,"very-high":6},"max_wbgt":31.48,"valid":24},"126":{"o":{"light":0,"moderate":3,"heavy":6,"very-high":6},"max_wbgt":30.63,"valid":24},"127":{"o":{"light":1,"moderate":6,"heavy":6,"very-high":6},"max_wbgt":32.55,"valid":24},"128":{"o":{"light":2,"moderate":5,"heavy":6,"very-high":6},"max_wbgt":32.4,"valid":24},"129":{"o":{"light":0,"moderate":4,"heavy":6,"very-high":6},"max_wbgt":31.47,"valid":24},"130":{"o":{"light":0,"moderate":3,"heavy":6,"very-high":6},"max_wbgt":30.07,"valid":24},"131":{"o":{"light":0,"moderate":3,"heavy":6,"very-high":6},"max_wbgt":30.44,"valid":24},"132":{"o":{"light":5,"moderate":6,"heavy":6,"very-high":6},"max_wbgt":32.62,"valid":24},"133":{"o":{"light":6,"moderate":6,"heavy":6,"very-high":6},"max_wbgt":32.63,"valid":24},"134":{"o":{"light":6,"moderate":6,"heavy":6,"very-high":6},"max_wbgt":36.22,"valid":24},"135":{"o":{"light":5,"moderate":6,"heavy":6,"very-high":6},"max_wbgt":34.28,"valid":24},"136":{"o":{"light":5,"moderate":6,"heavy":6,"very-high":6},"max_wbgt":34.31,"valid":24},"137":{"o":{"light":6,"moderate":6,"heavy":6,"very-high":6},"max_wbgt":33.52,"valid":24},"138":{"o":{"light":5,"moderate":6,"heavy":6,"very-high":6},"max_wbgt":32.97,"valid":24},"139":{"o":{"light":6,"moderate":6,"heavy":6,"very-high":6},"max_wbgt":32.49,"valid":24},"140":{"o":{"light":5,"moderate":6,"heavy":6,"very-high":6},"max_wbgt":32.55,"valid":24},"141":{"o":{"light":5,"moderate":6,"heavy":6,"very-high":6},"max_wbgt":32.54,"valid":24},"142":{"o":{"light":5,"moderate":6,"heavy":6,"very-high":6},"max_wbgt":32.85,"valid":24},"143":{"o":{"light":4,"moderate":6,"heavy":6,"very-high":6},"max_wbgt":33.07,"valid":24},"144":{"o":{"light":5,"moderate":6,"heavy":6,"very-high":6},"max_wbgt":32.77,"valid":24},"145":{"o":{"light":5,"moderate":6,"heavy":6,"very-high":6},"max_wbgt":32.6,"valid":24},"146":{"o":{"light":5,"moderate":6,"heavy":6,"very-high":6},"max_wbgt":32.46,"valid":24},"147":{"o":{"light":4,"moderate":6,"heavy":6,"very-high":6},"max_wbgt":32.67,"valid":24},"148":{"o":{"light":4,"moderate":6,"heavy":6,"very-high":6},"max_wbgt":33.22,"valid":24},"149":{"o":{"light":4,"moderate":6,"heavy":6,"very-high":6},"max_wbgt":33.67,"valid":24},"150":{"o":{"light":6,"moderate":6,"heavy":6,"very-high":6},"max_wbgt":34.64,"valid":24},"151":{"o":{"light":4,"moderate":6,"heavy":6,"very-high":6},"max_wbgt":35.39,"valid":24},"152":{"o":{"light":5,"moderate":6,"heavy":6,"very-high":6},"max_wbgt":35.51,"valid":24},"153":{"o":{"light":5,"moderate":7,"heavy":7,"very-high":7},"max_wbgt":34.32,"valid":24},"154":{"o":{"light":3,"moderate":5,"heavy":5,"very-high":5},"max_wbgt":35.0,"valid":24},"155":{"o":{"light":4,"moderate":6,"heavy":6,"very-high":6},"max_wbgt":36.7,"valid":24},"156":{"o":{"light":2,"moderate":6,"heavy":6,"very-high":6},"max_wbgt":34.84,"valid":24},"157":{"o":{"light":2,"moderate":4,"heavy":5,"very-high":5},"max_wbgt":37.09,"valid":24},"158":{"o":{"light":1,"moderate":5,"heavy":5,"very-high":5},"max_wbgt":33.63,"valid":24},"159":{"o":{"light":4,"moderate":6,"heavy":6,"very-high":6},"max_wbgt":34.2,"valid":24},"160":{"o":{"light":5,"moderate":6,"heavy":6,"very-high":6},"max_wbgt":34.11,"valid":24},"161":{"o":{"light":4,"moderate":6,"heavy":6,"very-high":6},"max_wbgt":32.84,"valid":24},"162":{"o":{"light":3,"moderate":6,"heavy":6,"very-high":6},"max_wbgt":33.24,"valid":24},"163":{"o":{"light":4,"moderate":6,"heavy":6,"very-high":6},"max_wbgt":33.16,"valid":24},"164":{"o":{"light":4,"moderate":6,"heavy":6,"very-high":6},"max_wbgt":33.64,"valid":24},"165":{"o":{"light":4,"moderate":6,"heavy":6,"very-high":6},"max_wbgt":34.08,"valid":24},"166":{"o":{"light":3,"moderate":6,"heavy":6,"very-high":6},"max_wbgt":32.39,"valid":24},"167":{"o":{"light":1,"moderate":4,"heavy":6,"very-high":6},"max_wbgt":31.48,"valid":24},"168":{"o":{"light":4,"moderate":6,"heavy":6,"very-high":6},"max_wbgt":32.21,"valid":24},"169":{"o":{"light":3,"moderate":6,"heavy":6,"very-high":6},"max_wbgt":32.07,"valid":24},"170":{"o":{"light":3,"moderate":6,"heavy":6,"very-high":6},"max_wbgt":32.8,"valid":24},"171":{"o":{"light":3,"moderate":6,"heavy":6,"very-high":6},"max_wbgt":32.86,"valid":24},"172":{"o":{"light":3,"moderate":6,"heavy":6,"very-high":6},"max_wbgt":33.62,"valid":24},"173":{"o":{"light":4,"moderate":7,"heavy":7,"very-high":7},"max_wbgt":33.75,"valid":24},"174":{"o":{"light":3,"moderate":7,"heavy":7,"very-high":7},"max_wbgt":33.32,"valid":24},"175":{"o":{"light":3,"moderate":7,"heavy":7,"very-high":7},"max_wbgt":33.43,"valid":24},"176":{"o":{"light":3,"moderate":6,"heavy":6,"very-high":6},"max_wbgt":38.56,"valid":24},"177":{"o":{"light":4,"moderate":6,"heavy":6,"very-high":6},"max_wbgt":36.79,"valid":24},"178":{"o":{"light":4,"moderate":6,"heavy":6,"very-high":6},"max_wbgt":35.2,"valid":24},"179":{"o":{"light":2,"moderate":6,"heavy":6,"very-high":6},"max_wbgt":35.63,"valid":24},"180":{"o":{"light":3,"moderate":5,"heavy":6,"very-high":6},"max_wbgt":34.17,"valid":24},"181":{"o":{"light":5,"moderate":7,"heavy":7,"very-high":7},"max_wbgt":34.79,"valid":24},"182":{"o":{"light":4,"moderate":5,"heavy":5,"very-high":5},"max_wbgt":34.52,"valid":24},"183":{"o":{"light":4,"moderate":6,"heavy":6,"very-high":6},"max_wbgt":35.91,"valid":24},"184":{"o":{"light":2,"moderate":6,"heavy":6,"very-high":6},"max_wbgt":33.77,"valid":24},"185":{"o":{"light":3,"moderate":6,"heavy":6,"very-high":6},"max_wbgt":35.42,"valid":24},"186":{"o":{"light":2,"moderate":5,"heavy":5,"very-high":5},"max_wbgt":33.09,"valid":24},"187":{"o":{"light":1,"moderate":4,"heavy":5,"very-high":5},"max_wbgt":33.16,"valid":24},"188":{"o":{"light":2,"moderate":4,"heavy":5,"very-high":5},"max_wbgt":33.81,"valid":24},"189":{"o":{"light":2,"moderate":5,"heavy":6,"very-high":6},"max_wbgt":34.26,"valid":24},"190":{"o":{"light":3,"moderate":6,"heavy":6,"very-high":6},"max_wbgt":33.85,"valid":24},"191":{"o":{"light":6,"moderate":7,"heavy":7,"very-high":7},"max_wbgt":34.73,"valid":24},"192":{"o":{"light":4,"moderate":7,"heavy":7,"very-high":7},"max_wbgt":37.27,"valid":24},"193":{"o":{"light":6,"moderate":7,"heavy":7,"very-high":7},"max_wbgt":34.26,"valid":24},"194":{"o":{"light":5,"moderate":7,"heavy":7,"very-high":7},"max_wbgt":34.41,"valid":24},"195":{"o":{"light":6,"moderate":7,"heavy":7,"very-high":7},"max_wbgt":35.78,"valid":24},"196":{"o":{"light":6,"moderate":7,"heavy":7,"very-high":7},"max_wbgt":35.74,"valid":24},"197":{"o":{"light":6,"moderate":7,"heavy":7,"very-high":7},"max_wbgt":35.69,"valid":24},"198":{"o":{"light":6,"moderate":7,"heavy":7,"very-high":7},"max_wbgt":34.1,"valid":24},"199":{"o":{"light":4,"moderate":7,"heavy":7,"very-high":7},"max_wbgt":33.39,"valid":24},"200":{"o":{"light":4,"moderate":7,"heavy":7,"very-high":7},"max_wbgt":33.6,"valid":24},"201":{"o":{"light":4,"moderate":6,"heavy":6,"very-high":6},"max_wbgt":33.47,"valid":24},"202":{"o":{"light":5,"moderate":6,"heavy":6,"very-high":6},"max_wbgt":33.65,"valid":24},"203":{"o":{"light":1,"moderate":5,"heavy":6,"very-high":6},"max_wbgt":32.7,"valid":24},"204":{"o":{"light":4,"moderate":7,"heavy":7,"very-high":7},"max_wbgt":32.91,"valid":24},"205":{"o":{"light":3,"moderate":7,"heavy":7,"very-high":7},"max_wbgt":32.62,"valid":24},"206":{"o":{"light":3,"moderate":7,"heavy":7,"very-high":7},"max_wbgt":32.57,"valid":24},"207":{"o":{"light":3,"moderate":7,"heavy":7,"very-high":7},"max_wbgt":33.94,"valid":24},"208":{"o":{"light":2,"moderate":7,"heavy":7,"very-high":7},"max_wbgt":33.26,"valid":24},"209":{"o":{"light":2,"moderate":5,"heavy":6,"very-high":6},"max_wbgt":33.47,"valid":24},"210":{"o":{"light":1,"moderate":5,"heavy":6,"very-high":6},"max_wbgt":33.02,"valid":24},"211":{"o":{"light":3,"moderate":6,"heavy":6,"very-high":6},"max_wbgt":33.98,"valid":24},"212":{"o":{"light":3,"moderate":6,"heavy":6,"very-high":6},"max_wbgt":33.53,"valid":24},"213":{"o":{"light":4,"moderate":6,"heavy":6,"very-high":6},"max_wbgt":33.85,"valid":24},"214":{"o":{"light":5,"moderate":6,"heavy":6,"very-high":6},"max_wbgt":33.96,"valid":24},"215":{"o":{"light":4,"moderate":7,"heavy":7,"very-high":7},"max_wbgt":36.94,"valid":24},"216":{"o":{"light":4,"moderate":7,"heavy":7,"very-high":7},"max_wbgt":33.72,"valid":24},"217":{"o":{"light":3,"moderate":7,"heavy":7,"very-high":7},"max_wbgt":35.04,"valid":24},"218":{"o":{"light":3,"moderate":7,"heavy":7,"very-high":7},"max_wbgt":33.3,"valid":24},"219":{"o":{"light":5,"moderate":7,"heavy":7,"very-high":7},"max_wbgt":33.45,"valid":24},"220":{"o":{"light":4,"moderate":7,"heavy":7,"very-high":7},"max_wbgt":34.27,"valid":24},"221":{"o":{"light":4,"moderate":7,"heavy":7,"very-high":7},"max_wbgt":33.52,"valid":24},"222":{"o":{"light":4,"moderate":7,"heavy":7,"very-high":7},"max_wbgt":33.58,"valid":24},"223":{"o":{"light":5,"moderate":6,"heavy":6,"very-high":6},"max_wbgt":33.6,"valid":24},"224":{"o":{"light":3,"moderate":6,"heavy":6,"very-high":6},"max_wbgt":33.24,"valid":24},"225":{"o":{"light":4,"moderate":6,"heavy":6,"very-high":6},"max_wbgt":32.65,"valid":24},"226":{"o":{"light":2,"moderate":6,"heavy":6,"very-high":6},"max_wbgt":32.32,"valid":24},"227":{"o":{"light":5,"moderate":7,"heavy":7,"very-high":7},"max_wbgt":33.68,"valid":24},"228":{"o":{"light":4,"moderate":6,"heavy":6,"very-high":6},"max_wbgt":34.07,"valid":24},"229":{"o":{"light":4,"moderate":7,"heavy":7,"very-high":7},"max_wbgt":35.13,"valid":24},"230":{"o":{"light":4,"moderate":7,"heavy":7,"very-high":7},"max_wbgt":35.24,"valid":24},"231":{"o":{"light":6,"moderate":7,"heavy":7,"very-high":7},"max_wbgt":34.88,"valid":24},"232":{"o":{"light":6,"moderate":7,"heavy":7,"very-high":7},"max_wbgt":35.7,"valid":24},"233":{"o":{"light":6,"moderate":7,"heavy":7,"very-high":7},"max_wbgt":34.87,"valid":24},"234":{"o":{"light":6,"moderate":7,"heavy":7,"very-high":7},"max_wbgt":40.36,"valid":24},"235":{"o":{"light":6,"moderate":7,"heavy":7,"very-high":7},"max_wbgt":36.49,"valid":24},"236":{"o":{"light":4,"moderate":7,"heavy":7,"very-high":7},"max_wbgt":35.5,"valid":24},"237":{"o":{"light":3,"moderate":7,"heavy":7,"very-high":7},"max_wbgt":33.66,"valid":24},"238":{"o":{"light":5,"moderate":6,"heavy":6,"very-high":6},"max_wbgt":33.42,"valid":24},"239":{"o":{"light":5,"moderate":7,"heavy":7,"very-high":7},"max_wbgt":35.4,"valid":24},"240":{"o":{"light":6,"moderate":7,"heavy":7,"very-high":7},"max_wbgt":35.87,"valid":24},"241":{"o":{"light":0,"moderate":0,"heavy":0,"very-high":0},"max_wbgt":17.89,"valid":24},"242":{"o":{"light":0,"moderate":0,"heavy":1,"very-high":1},"max_wbgt":26.34,"valid":24},"243":{"o":{"light":0,"moderate":0,"heavy":0,"very-high":1},"max_wbgt":25.48,"valid":24},"244":{"o":{"light":0,"moderate":0,"heavy":0,"very-high":0},"max_wbgt":22.96,"valid":24},"245":{"o":{"light":0,"moderate":0,"heavy":0,"very-high":0},"max_wbgt":15.56,"valid":24},"246":{"o":{"light":0,"moderate":0,"heavy":1,"very-high":3},"max_wbgt":27.65,"valid":24},"247":{"o":{"light":0,"moderate":3,"heavy":5,"very-high":6},"max_wbgt":28.99,"valid":24},"248":{"o":{"light":0,"moderate":0,"heavy":0,"very-high":4},"max_wbgt":26.77,"valid":24},"249":{"o":{"light":2,"moderate":4,"heavy":4,"very-high":5},"max_wbgt":31.23,"valid":24},"250":{"o":{"light":0,"moderate":1,"heavy":2,"very-high":3},"max_wbgt":28.31,"valid":24},"251":{"o":{"light":2,"moderate":5,"heavy":6,"very-high":6},"max_wbgt":32.12,"valid":24},"252":{"o":{"light":0,"moderate":0,"heavy":0,"very-high":0},"max_wbgt":26.74,"valid":24},"253":{"o":{"light":1,"moderate":6,"heavy":6,"very-high":6},"max_wbgt":32.94,"valid":24},"254":{"o":{"light":0,"moderate":0,"heavy":0,"very-high":1},"max_wbgt":30.81,"valid":24},"255":{"o":{"light":0,"moderate":0,"heavy":1,"very-high":2},"max_wbgt":26.8,"valid":24},"256":{"o":{"light":0,"moderate":0,"heavy":1,"very-high":2},"max_wbgt":27.96,"valid":24},"257":{"o":{"light":0,"moderate":0,"heavy":0,"very-high":0},"max_wbgt":20.54,"valid":24},"258":{"o":{"light":0,"moderate":0,"heavy":0,"very-high":0},"max_wbgt":25.15,"valid":24},"259":{"o":{"light":1,"moderate":3,"heavy":5,"very-high":5},"max_wbgt":33.13,"valid":24},"260":{"o":{"light":0,"moderate":0,"heavy":0,"very-high":0},"max_wbgt":22.03,"valid":24},"261":{"o":{"light":3,"moderate":5,"heavy":5,"very-high":6},"max_wbgt":33.04,"valid":24},"262":{"o":{"light":0,"moderate":5,"heavy":6,"very-high":6},"max_wbgt":32.62,"valid":24},"263":{"o":{"light":0,"moderate":0,"heavy":0,"very-high":1},"max_wbgt":25.46,"valid":24},"264":{"o":{"light":0,"moderate":5,"heavy":6,"very-high":6},"max_wbgt":30.81,"valid":24},"265":{"o":{"light":4,"moderate":6,"heavy":6,"very-high":6},"max_wbgt":33.41,"valid":24},"266":{"o":{"light":1,"moderate":3,"heavy":4,"very-high":4},"max_wbgt":31.24,"valid":24},"267":{"o":{"light":0,"moderate":0,"heavy":1,"very-high":2},"max_wbgt":27.58,"valid":24},"268":{"o":{"light":0,"moderate":3,"heavy":3,"very-high":4},"max_wbgt":29.4,"valid":24},"269":{"o":{"light":2,"moderate":3,"heavy":3,"very-high":5},"max_wbgt":32.75,"valid":24},"270":{"o":{"light":0,"moderate":4,"heavy":5,"very-high":5},"max_wbgt":31.18,"valid":24},"271":{"o":{"light":3,"moderate":4,"heavy":5,"very-high":6},"max_wbgt":30.73,"valid":24},"272":{"o":{"light":0,"moderate":3,"heavy":5,"very-high":5},"max_wbgt":30.82,"valid":24},"273":{"o":{"light":0,"moderate":2,"heavy":3,"very-high":4},"max_wbgt":28.31,"valid":24},"274":{"o":{"light":3,"moderate":3,"heavy":5,"very-high":5},"max_wbgt":31.72,"valid":24},"275":{"o":{"light":2,"moderate":3,"heavy":4,"very-high":5},"max_wbgt":34.87,"valid":24},"276":{"o":{"light":1,"moderate":3,"heavy":5,"very-high":5},"max_wbgt":34.09,"valid":24},"277":{"o":{"light":2,"moderate":5,"heavy":6,"very-high":6},"max_wbgt":32.53,"valid":24},"278":{"o":{"light":3,"moderate":5,"heavy":6,"very-high":6},"max_wbgt":35.35,"valid":24},"279":{"o":{"light":0,"moderate":0,"heavy":0,"very-high":0},"max_wbgt":22.33,"valid":24},"280":{"o":{"light":0,"moderate":4,"heavy":5,"very-high":6},"max_wbgt":31.09,"valid":24},"281":{"o":{"light":4,"moderate":5,"heavy":6,"very-high":6},"max_wbgt":35.19,"valid":24},"282":{"o":{"light":3,"moderate":6,"heavy":6,"very-high":6},"max_wbgt":36.22,"valid":24},"283":{"o":{"light":3,"moderate":4,"heavy":4,"very-high":4},"max_wbgt":35.47,"valid":24},"284":{"o":{"light":0,"moderate":0,"heavy":0,"very-high":2},"max_wbgt":27.63,"valid":24},"285":{"o":{"light":4,"moderate":5,"heavy":5,"very-high":6},"max_wbgt":32.77,"valid":24},"286":{"o":{"light":4,"moderate":5,"heavy":5,"very-high":5},"max_wbgt":30.56,"valid":24},"287":{"o":{"light":0,"moderate":3,"heavy":5,"very-high":5},"max_wbgt":29.4,"valid":24},"288":{"o":{"light":0,"moderate":0,"heavy":0,"very-high":1},"max_wbgt":25.18,"valid":24},"289":{"o":{"light":2,"moderate":6,"heavy":6,"very-high":6},"max_wbgt":31.55,"valid":24},"290":{"o":{"light":2,"moderate":5,"heavy":6,"very-high":6},"max_wbgt":31.19,"valid":24},"291":{"o":{"light":4,"moderate":5,"heavy":6,"very-high":6},"max_wbgt":31.67,"valid":24},"292":{"o":{"light":3,"moderate":5,"heavy":6,"very-high":6},"max_wbgt":33.87,"valid":24},"293":{"o":{"light":0,"moderate":4,"heavy":6,"very-high":6},"max_wbgt":30.69,"valid":24},"294":{"o":{"light":0,"moderate":5,"heavy":6,"very-high":6},"max_wbgt":30.67,"valid":24},"295":{"o":{"light":2,"moderate":4,"heavy":6,"very-high":6},"max_wbgt":31.79,"valid":24},"296":{"o":{"light":0,"moderate":0,"heavy":0,"very-high":1},"max_wbgt":26.05,"valid":24},"297":{"o":{"light":2,"moderate":6,"heavy":6,"very-high":6},"max_wbgt":35.19,"valid":24},"298":{"o":{"light":0,"moderate":0,"heavy":0,"very-high":0},"max_wbgt":25.4,"valid":24},"299":{"o":{"light":0,"moderate":0,"heavy":0,"very-high":2},"max_wbgt":26.8,"valid":24},"300":{"o":{"light":5,"moderate":6,"heavy":6,"very-high":6},"max_wbgt":36.13,"valid":24},"301":{"o":{"light":4,"moderate":6,"heavy":6,"very-high":6},"max_wbgt":33.68,"valid":24},"302":{"o":{"light":3,"moderate":6,"heavy":6,"very-high":6},"max_wbgt":32.59,"valid":24},"303":{"o":{"light":5,"moderate":6,"heavy":6,"very-high":6},"max_wbgt":33.08,"valid":24},"304":{"o":{"light":5,"moderate":6,"heavy":6,"very-high":6},"max_wbgt":34.27,"valid":24},"305":{"o":{"light":3,"moderate":6,"heavy":6,"very-high":6},"max_wbgt":39.23,"valid":24},"306":{"o":{"light":2,"moderate":5,"heavy":6,"very-high":6},"max_wbgt":33.04,"valid":24},"307":{"o":{"light":0,"moderate":4,"heavy":5,"very-high":5},"max_wbgt":32.42,"valid":24},"308":{"o":{"light":0,"moderate":3,"heavy":5,"very-high":5},"max_wbgt":34.22,"valid":24},"309":{"o":{"light":3,"moderate":5,"heavy":6,"very-high":6},"max_wbgt":33.09,"valid":24},"310":{"o":{"light":2,"moderate":4,"heavy":5,"very-high":5},"max_wbgt":32.53,"valid":24},"311":{"o":{"light":4,"moderate":5,"heavy":5,"very-high":5},"max_wbgt":32.7,"valid":24},"312":{"o":{"light":1,"moderate":5,"heavy":5,"very-high":5},"max_wbgt":33.24,"valid":24},"313":{"o":{"light":3,"moderate":5,"heavy":6,"very-high":6},"max_wbgt":33.42,"valid":24},"314":{"o":{"light":4,"moderate":6,"heavy":6,"very-high":6},"max_wbgt":32.31,"valid":24},"315":{"o":{"light":1,"moderate":4,"heavy":5,"very-high":6},"max_wbgt":30.74,"valid":24},"316":{"o":{"light":3,"moderate":5,"heavy":6,"very-high":6},"max_wbgt":36.75,"valid":24},"317":{"o":{"light":3,"moderate":6,"heavy":6,"very-high":6},"max_wbgt":41.06,"valid":24},"318":{"o":{"light":3,"moderate":6,"heavy":6,"very-high":6},"max_wbgt":38.77,"valid":24},"319":{"o":{"light":6,"moderate":6,"heavy":6,"very-high":6},"max_wbgt":32.98,"valid":24},"320":{"o":{"light":4,"moderate":6,"heavy":6,"very-high":6},"max_wbgt":34.42,"valid":24},"321":{"o":{"light":6,"moderate":6,"heavy":6,"very-high":6},"max_wbgt":37.4,"valid":24},"322":{"o":{"light":3,"moderate":6,"heavy":6,"very-high":6},"max_wbgt":34.58,"valid":24},"323":{"o":{"light":6,"moderate":6,"heavy":6,"very-high":6},"max_wbgt":33.74,"valid":24},"324":{"o":{"light":4,"moderate":6,"heavy":6,"very-high":6},"max_wbgt":32.7,"valid":24},"325":{"o":{"light":5,"moderate":6,"heavy":6,"very-high":6},"max_wbgt":32.89,"valid":24},"326":{"o":{"light":3,"moderate":6,"heavy":6,"very-high":6},"max_wbgt":33.47,"valid":24},"327":{"o":{"light":0,"moderate":1,"heavy":4,"very-high":6},"max_wbgt":34.53,"valid":24},"328":{"o":{"light":2,"moderate":6,"heavy":6,"very-high":6},"max_wbgt":33.24,"valid":24},"329":{"o":{"light":4,"moderate":6,"heavy":6,"very-high":6},"max_wbgt":33.81,"valid":24},"330":{"o":{"light":3,"moderate":6,"heavy":6,"very-high":6},"max_wbgt":33.7,"valid":24},"331":{"o":{"light":4,"moderate":6,"heavy":6,"very-high":6},"max_wbgt":32.75,"valid":24},"332":{"o":{"light":3,"moderate":6,"heavy":6,"very-high":6},"max_wbgt":32.78,"valid":24},"333":{"o":{"light":2,"moderate":6,"heavy":6,"very-high":6},"max_wbgt":32.11,"valid":24},"334":{"o":{"light":3,"moderate":5,"heavy":6,"very-high":6},"max_wbgt":32.38,"valid":24},"335":{"o":{"light":2,"moderate":6,"heavy":6,"very-high":6},"max_wbgt":32.65,"valid":24},"336":{"o":{"light":2,"moderate":6,"heavy":6,"very-high":6},"max_wbgt":32.1,"valid":24},"337":{"o":{"light":2,"moderate":6,"heavy":6,"very-high":6},"max_wbgt":31.82,"valid":24},"338":{"o":{"light":2,"moderate":6,"heavy":6,"very-high":6},"max_wbgt":32.09,"valid":24},"339":{"o":{"light":2,"moderate":6,"heavy":6,"very-high":6},"max_wbgt":32.65,"valid":24},"340":{"o":{"light":2,"moderate":6,"heavy":6,"very-high":6},"max_wbgt":31.69,"valid":24},"341":{"o":{"light":2,"moderate":6,"heavy":6,"very-high":6},"max_wbgt":33.03,"valid":24},"342":{"o":{"light":2,"moderate":6,"heavy":6,"very-high":6},"max_wbgt":32.91,"valid":24},"343":{"o":{"light":3,"moderate":6,"heavy":6,"very-high":6},"max_wbgt":32.16,"valid":24},"344":{"o":{"light":2,"moderate":6,"heavy":6,"very-high":6},"max_wbgt":32.42,"valid":24},"345":{"o":{"light":2,"moderate":6,"heavy":6,"very-high":6},"max_wbgt":33.2,"valid":24},"346":{"o":{"light":4,"moderate":6,"heavy":6,"very-high":6},"max_wbgt":34.04,"valid":24},"347":{"o":{"light":2,"moderate":5,"heavy":6,"very-high":6},"max_wbgt":32.56,"valid":24},"348":{"o":{"light":3,"moderate":5,"heavy":7,"very-high":7},"max_wbgt":32.96,"valid":24},"349":{"o":{"light":3,"moderate":6,"heavy":6,"very-high":6},"max_wbgt":31.87,"valid":24},"350":{"o":{"light":2,"moderate":6,"heavy":6,"very-high":6},"max_wbgt":32.49,"valid":24},"351":{"o":{"light":3,"moderate":6,"heavy":6,"very-high":6},"max_wbgt":32.51,"valid":24},"352":{"o":{"light":3,"moderate":6,"heavy":6,"very-high":6},"max_wbgt":32.38,"valid":24},"353":{"o":{"light":2,"moderate":6,"heavy":6,"very-high":6},"max_wbgt":31.91,"valid":24},"354":{"o":{"light":2,"moderate":6,"heavy":6,"very-high":6},"max_wbgt":32.18,"valid":24},"355":{"o":{"light":2,"moderate":6,"heavy":6,"very-high":6},"max_wbgt":33.08,"valid":24},"356":{"o":{"light":0,"moderate":2,"heavy":3,"very-high":4},"max_wbgt":30.02,"valid":24},"357":{"o":{"light":1,"moderate":6,"heavy":6,"very-high":6},"max_wbgt":32.76,"valid":24},"358":{"o":{"light":4,"moderate":7,"heavy":7,"very-high":7},"max_wbgt":38.69,"valid":24},"359":{"o":{"light":3,"moderate":5,"heavy":6,"very-high":6},"max_wbgt":34.05,"valid":24},"360":{"o":{"light":1,"moderate":4,"heavy":6,"very-high":7},"max_wbgt":31.34,"valid":24},"361":{"o":{"light":2,"moderate":6,"heavy":7,"very-high":7},"max_wbgt":32.69,"valid":24},"362":{"o":{"light":2,"moderate":6,"heavy":6,"very-high":6},"max_wbgt":31.88,"valid":24},"363":{"o":{"light":2,"moderate":6,"heavy":6,"very-high":6},"max_wbgt":32.58,"valid":24},"364":{"o":{"light":0,"moderate":3,"heavy":6,"very-high":7},"max_wbgt":30.7,"valid":24},"365":{"o":{"light":1,"moderate":3,"heavy":4,"very-high":6},"max_wbgt":31.44,"valid":24},"366":{"o":{"light":0,"moderate":2,"heavy":4,"very-high":6},"max_wbgt":30.31,"valid":24},"367":{"o":{"light":1,"moderate":2,"heavy":5,"very-high":6},"max_wbgt":31.18,"valid":24},"368":{"o":{"light":1,"moderate":4,"heavy":6,"very-high":6},"max_wbgt":31.17,"valid":24},"369":{"o":{"light":2,"moderate":6,"heavy":6,"very-high":6},"max_wbgt":31.9,"valid":24},"370":{"o":{"light":0,"moderate":0,"heavy":3,"very-high":4},"max_wbgt":28.89,"valid":24},"371":{"o":{"light":0,"moderate":2,"heavy":4,"very-high":5},"max_wbgt":31.57,"valid":24},"372":{"o":{"light":0,"moderate":0,"heavy":2,"very-high":4},"max_wbgt":29.84,"valid":24},"373":{"o":{"light":0,"moderate":0,"heavy":2,"very-high":4},"max_wbgt":30.23,"valid":24},"374":{"o":{"light":0,"moderate":2,"heavy":4,"very-high":5},"max_wbgt":32.01,"valid":24},"375":{"o":{"light":0,"moderate":2,"heavy":6,"very-high":6},"max_wbgt":30.08,"valid":24},"376":{"o":{"light":0,"moderate":0,"heavy":1,"very-high":2},"max_wbgt":27.67,"valid":24},"377":{"o":{"light":2,"moderate":6,"heavy":6,"very-high":6},"max_wbgt":35.43,"valid":24},"378":{"o":{"light":0,"moderate":6,"heavy":6,"very-high":6},"max_wbgt":32.61,"valid":24},"379":{"o":{"light":0,"moderate":2,"heavy":4,"very-high":4},"max_wbgt":31.03,"valid":24},"380":{"o":{"light":0,"moderate":0,"heavy":3,"very-high":4},"max_wbgt":28.9,"valid":24},"381":{"o":{"light":0,"moderate":0,"heavy":2,"very-high":3},"max_wbgt":29.73,"valid":24},"382":{"o":{"light":0,"moderate":4,"heavy":5,"very-high":5},"max_wbgt":29.28,"valid":24},"383":{"o":{"light":0,"moderate":0,"heavy":3,"very-high":4},"max_wbgt":28.71,"valid":24},"384":{"o":{"light":0,"moderate":1,"heavy":2,"very-high":3},"max_wbgt":28.97,"valid":24},"385":{"o":{"light":0,"moderate":0,"heavy":2,"very-high":3},"max_wbgt":28.97,"valid":24},"386":{"o":{"light":0,"moderate":0,"heavy":2,"very-high":3},"max_wbgt":27.25,"valid":24},"387":{"o":{"light":0,"moderate":1,"heavy":2,"very-high":5},"max_wbgt":27.87,"valid":24},"388":{"o":{"light":0,"moderate":1,"heavy":3,"very-high":3},"max_wbgt":29.18,"valid":24},"389":{"o":{"light":0,"moderate":0,"heavy":0,"very-high":0},"max_wbgt":22.76,"valid":24},"390":{"o":{"light":0,"moderate":0,"heavy":0,"very-high":0},"max_wbgt":25.91,"valid":24},"391":{"o":{"light":0,"moderate":0,"heavy":0,"very-high":1},"max_wbgt":26.65,"valid":24},"392":{"o":{"light":0,"moderate":0,"heavy":1,"very-high":4},"max_wbgt":28.33,"valid":24},"393":{"o":{"light":0,"moderate":0,"heavy":0,"very-high":3},"max_wbgt":28.09,"valid":24},"394":{"o":{"light":0,"moderate":0,"heavy":0,"very-high":0},"max_wbgt":26.0,"valid":24},"395":{"o":{"light":0,"moderate":0,"heavy":0,"very-high":2},"max_wbgt":27.48,"valid":24},"396":{"o":{"light":0,"moderate":0,"heavy":0,"very-high":0},"max_wbgt":28.05,"valid":24},"397":{"o":{"light":0,"moderate":0,"heavy":0,"very-high":0},"max_wbgt":26.18,"valid":24},"398":{"o":{"light":0,"moderate":0,"heavy":0,"very-high":0},"max_wbgt":25.05,"valid":24},"399":{"o":{"light":0,"moderate":2,"heavy":4,"very-high":5},"max_wbgt":30.85,"valid":24},"400":{"o":{"light":0,"moderate":3,"heavy":5,"very-high":7},"max_wbgt":29.99,"valid":24},"401":{"o":{"light":1,"moderate":6,"heavy":7,"very-high":7},"max_wbgt":31.2,"valid":24},"402":{"o":{"light":4,"moderate":6,"heavy":6,"very-high":6},"max_wbgt":35.82,"valid":24},"403":{"o":{"light":1,"moderate":3,"heavy":4,"very-high":5},"max_wbgt":32.91,"valid":24},"404":{"o":{"light":2,"moderate":5,"heavy":5,"very-high":5},"max_wbgt":33.79,"valid":24},"405":{"o":{"light":0,"moderate":3,"heavy":5,"very-high":5},"max_wbgt":31.44,"valid":24},"406":{"o":{"light":0,"moderate":4,"heavy":6,"very-high":6},"max_wbgt":32.45,"valid":24},"407":{"o":{"light":0,"moderate":3,"heavy":5,"very-high":5},"max_wbgt":31.41,"valid":24},"408":{"o":{"light":0,"moderate":0,"heavy":3,"very-high":4},"max_wbgt":29.32,"valid":24},"409":{"o":{"light":0,"moderate":0,"heavy":4,"very-high":5},"max_wbgt":29.73,"valid":24},"410":{"o":{"light":0,"moderate":0,"heavy":1,"very-high":3},"max_wbgt":29.26,"valid":24},"411":{"o":{"light":0,"moderate":0,"heavy":2,"very-high":3},"max_wbgt":29.45,"valid":24},"412":{"o":{"light":0,"moderate":0,"heavy":1,"very-high":4},"max_wbgt":28.41,"valid":24},"413":{"o":{"light":0,"moderate":0,"heavy":3,"very-high":4},"max_wbgt":27.41,"valid":24},"414":{"o":{"light":0,"moderate":0,"heavy":0,"very-high":2},"max_wbgt":26.16,"valid":24},"415":{"o":{"light":0,"moderate":0,"heavy":1,"very-high":1},"max_wbgt":26.64,"valid":24},"416":{"o":{"light":0,"moderate":0,"heavy":3,"very-high":4},"max_wbgt":28.76,"valid":24},"417":{"o":{"light":0,"moderate":5,"heavy":5,"very-high":5},"max_wbgt":29.78,"valid":24},"418":{"o":{"light":1,"moderate":5,"heavy":6,"very-high":6},"max_wbgt":31.21,"valid":24},"419":{"o":{"light":4,"moderate":6,"heavy":6,"very-high":6},"max_wbgt":32.58,"valid":24},"420":{"o":{"light":4,"moderate":6,"heavy":6,"very-high":6},"max_wbgt":32.36,"valid":24},"421":{"o":{"light":2,"moderate":6,"heavy":6,"very-high":6},"max_wbgt":31.92,"valid":24},"422":{"o":{"light":4,"moderate":6,"heavy":6,"very-high":6},"max_wbgt":32.4,"valid":24},"423":{"o":{"light":0,"moderate":5,"heavy":6,"very-high":6},"max_wbgt":31.75,"valid":24},"424":{"o":{"light":2,"moderate":5,"heavy":6,"very-high":6},"max_wbgt":31.98,"valid":24},"425":{"o":{"light":2,"moderate":6,"heavy":6,"very-high":6},"max_wbgt":31.63,"valid":24},"426":{"o":{"light":2,"moderate":6,"heavy":6,"very-high":6},"max_wbgt":31.97,"valid":24},"427":{"o":{"light":0,"moderate":3,"heavy":5,"very-high":6},"max_wbgt":30.69,"valid":24},"428":{"o":{"light":1,"moderate":5,"heavy":6,"very-high":6},"max_wbgt":31.51,"valid":24},"429":{"o":{"light":2,"moderate":6,"heavy":6,"very-high":6},"max_wbgt":32.12,"valid":24},"430":{"o":{"light":2,"moderate":7,"heavy":7,"very-high":7},"max_wbgt":31.87,"valid":24},"431":{"o":{"light":0,"moderate":4,"heavy":5,"very-high":6},"max_wbgt":31.32,"valid":24},"432":{"o":{"light":0,"moderate":3,"heavy":6,"very-high":6},"max_wbgt":30.34,"valid":24},"433":{"o":{"light":0,"moderate":5,"heavy":6,"very-high":6},"max_wbgt":31.03,"valid":24},"434":{"o":{"light":0,"moderate":2,"heavy":5,"very-high":6},"max_wbgt":29.56,"valid":24},"435":{"o":{"light":0,"moderate":3,"heavy":6,"very-high":6},"max_wbgt":30.0,"valid":24},"436":{"o":{"light":0,"moderate":3,"heavy":6,"very-high":6},"max_wbgt":30.6,"valid":24},"437":{"o":{"light":0,"moderate":3,"heavy":6,"very-high":6},"max_wbgt":29.93,"valid":24},"438":{"o":{"light":0,"moderate":1,"heavy":5,"very-high":6},"max_wbgt":29.47,"valid":24},"439":{"o":{"light":0,"moderate":3,"heavy":5,"very-high":6},"max_wbgt":29.89,"valid":24},"440":{"o":{"light":0,"moderate":6,"heavy":6,"very-high":6},"max_wbgt":31.24,"valid":24},"441":{"o":{"light":0,"moderate":1,"heavy":4,"very-high":6},"max_wbgt":30.7,"valid":24},"442":{"o":{"light":0,"moderate":5,"heavy":6,"very-high":6},"max_wbgt":31.3,"valid":24},"443":{"o":{"light":0,"moderate":5,"heavy":6,"very-high":6},"max_wbgt":30.92,"valid":24},"444":{"o":{"light":0,"moderate":3,"heavy":6,"very-high":6},"max_wbgt":30.56,"valid":24},"445":{"o":{"light":0,"moderate":3,"heavy":6,"very-high":6},"max_wbgt":30.54,"valid":24},"446":{"o":{"light":0,"moderate":3,"heavy":6,"very-high":6},"max_wbgt":30.63,"valid":24},"447":{"o":{"light":0,"moderate":0,"heavy":3,"very-high":6},"max_wbgt":29.37,"valid":24},"448":{"o":{"light":0,"moderate":5,"heavy":6,"very-high":6},"max_wbgt":31.44,"valid":24},"449":{"o":{"light":0,"moderate":4,"heavy":6,"very-high":6},"max_wbgt":31.25,"valid":24},"450":{"o":{"light":0,"moderate":3,"heavy":6,"very-high":6},"max_wbgt":30.92,"valid":24},"451":{"o":{"light":0,"moderate":4,"heavy":5,"very-high":6},"max_wbgt":30.98,"valid":24},"452":{"o":{"light":0,"moderate":4,"heavy":6,"very-high":6},"max_wbgt":31.31,"valid":24},"453":{"o":{"light":0,"moderate":1,"heavy":4,"very-high":5},"max_wbgt":29.43,"valid":24},"454":{"o":{"light":0,"moderate":3,"heavy":6,"very-high":6},"max_wbgt":30.57,"valid":24},"455":{"o":{"light":0,"moderate":0,"heavy":3,"very-high":5},"max_wbgt":29.3,"valid":24},"456":{"o":{"light":0,"moderate":2,"heavy":4,"very-high":5},"max_wbgt":29.48,"valid":24},"457":{"o":{"light":0,"moderate":1,"heavy":5,"very-high":6},"max_wbgt":28.66,"valid":24},"458":{"o":{"light":0,"moderate":4,"heavy":6,"very-high":6},"max_wbgt":30.44,"valid":24},"459":{"o":{"light":0,"moderate":5,"heavy":6,"very-high":6},"max_wbgt":31.26,"valid":24},"460":{"o":{"light":0,"moderate":5,"heavy":6,"very-high":6},"max_wbgt":31.31,"valid":24},"461":{"o":{"light":0,"moderate":3,"heavy":4,"very-high":6},"max_wbgt":30.12,"valid":24},"462":{"o":{"light":1,"moderate":7,"heavy":7,"very-high":7},"max_wbgt":31.83,"valid":24},"463":{"o":{"light":2,"moderate":6,"heavy":7,"very-high":7},"max_wbgt":32.22,"valid":24},"464":{"o":{"light":0,"moderate":3,"heavy":6,"very-high":6},"max_wbgt":30.24,"valid":24},"465":{"o":{"light":0,"moderate":3,"heavy":6,"very-high":6},"max_wbgt":30.52,"valid":24},"466":{"o":{"light":0,"moderate":6,"heavy":6,"very-high":6},"max_wbgt":31.46,"valid":24},"467":{"o":{"light":1,"moderate":6,"heavy":6,"very-high":6},"max_wbgt":32.31,"valid":24},"468":{"o":{"light":2,"moderate":6,"heavy":7,"very-high":7},"max_wbgt":31.71,"valid":24},"469":{"o":{"light":0,"moderate":6,"heavy":6,"very-high":6},"max_wbgt":31.64,"valid":24},"470":{"o":{"light":1,"moderate":6,"heavy":6,"very-high":6},"max_wbgt":31.85,"valid":24},"471":{"o":{"light":2,"moderate":6,"heavy":6,"very-high":6},"max_wbgt":32.14,"valid":24},"472":{"o":{"light":0,"moderate":6,"heavy":6,"very-high":6},"max_wbgt":31.48,"valid":24},"473":{"o":{"light":1,"moderate":6,"heavy":6,"very-high":6},"max_wbgt":31.98,"valid":24},"474":{"o":{"light":2,"moderate":6,"heavy":6,"very-high":6},"max_wbgt":32.47,"valid":24},"475":{"o":{"light":2,"moderate":6,"heavy":6,"very-high":6},"max_wbgt":31.07,"valid":24},"476":{"o":{"light":0,"moderate":6,"heavy":6,"very-high":6},"max_wbgt":32.0,"valid":24},"477":{"o":{"light":1,"moderate":6,"heavy":6,"very-high":6},"max_wbgt":31.77,"valid":24},"478":{"o":{"light":1,"moderate":6,"heavy":7,"very-high":7},"max_wbgt":30.78,"valid":24},"479":{"o":{"light":0,"moderate":5,"heavy":6,"very-high":6},"max_wbgt":30.34,"valid":24},"480":{"o":{"light":1,"moderate":6,"heavy":6,"very-high":6},"max_wbgt":31.64,"valid":24},"481":{"o":{"light":2,"moderate":6,"heavy":6,"very-high":6},"max_wbgt":31.53,"valid":24},"482":{"o":{"light":1,"moderate":6,"heavy":6,"very-high":6},"max_wbgt":32.25,"valid":24},"483":{"o":{"light":1,"moderate":6,"heavy":6,"very-high":6},"max_wbgt":32.13,"valid":24},"484":{"o":{"light":0,"moderate":6,"heavy":6,"very-high":6},"max_wbgt":31.88,"valid":24},"485":{"o":{"light":0,"moderate":3,"heavy":6,"very-high":6},"max_wbgt":30.37,"valid":24},"486":{"o":{"light":1,"moderate":6,"heavy":6,"very-high":6},"max_wbgt":31.65,"valid":24},"487":{"o":{"light":0,"moderate":3,"heavy":6,"very-high":6},"max_wbgt":30.72,"valid":24},"488":{"o":{"light":1,"moderate":6,"heavy":6,"very-high":6},"max_wbgt":31.45,"valid":24},"489":{"o":{"light":0,"moderate":1,"heavy":3,"very-high":5},"max_wbgt":28.81,"valid":24},"490":{"o":{"light":1,"moderate":3,"heavy":6,"very-high":6},"max_wbgt":30.88,"valid":24},"491":{"o":{"light":0,"moderate":3,"heavy":4,"very-high":5},"max_wbgt":30.7,"valid":24},"492":{"o":{"light":1,"moderate":4,"heavy":6,"very-high":6},"max_wbgt":31.03,"valid":24},"493":{"o":{"light":0,"moderate":4,"heavy":6,"very-high":6},"max_wbgt":30.93,"valid":24},"494":{"o":{"light":0,"moderate":5,"heavy":6,"very-high":6},"max_wbgt":30.94,"valid":24},"495":{"o":{"light":0,"moderate":4,"heavy":6,"very-high":6},"max_wbgt":30.3,"valid":24},"496":{"o":{"light":0,"moderate":3,"heavy":6,"very-high":6},"max_wbgt":30.6,"valid":24},"497":{"o":{"light":0,"moderate":3,"heavy":6,"very-high":6},"max_wbgt":31.08,"valid":24},"498":{"o":{"light":0,"moderate":3,"heavy":6,"very-high":6},"max_wbgt":30.76,"valid":24},"499":{"o":{"light":0,"moderate":6,"heavy":6,"very-high":6},"max_wbgt":31.26,"valid":24},"500":{"o":{"light":0,"moderate":3,"heavy":6,"very-high":6},"max_wbgt":30.4,"valid":24},"501":{"o":{"light":0,"moderate":4,"heavy":6,"very-high":6},"max_wbgt":31.43,"valid":24},"502":{"o":{"light":0,"moderate":3,"heavy":5,"very-high":6},"max_wbgt":30.13,"valid":24},"503":{"o":{"light":0,"moderate":5,"heavy":6,"very-high":6},"max_wbgt":31.21,"valid":24},"504":{"o":{"light":0,"moderate":4,"heavy":6,"very-high":6},"max_wbgt":31.72,"valid":24},"505":{"o":{"light":0,"moderate":4,"heavy":5,"very-high":5},"max_wbgt":31.45,"valid":24},"506":{"o":{"light":1,"moderate":2,"heavy":5,"very-high":6},"max_wbgt":32.29,"valid":24},"507":{"o":{"light":0,"moderate":1,"heavy":5,"very-high":5},"max_wbgt":29.03,"valid":24},"508":{"o":{"light":0,"moderate":4,"heavy":5,"very-high":5},"max_wbgt":29.26,"valid":24},"509":{"o":{"light":0,"moderate":4,"heavy":5,"very-high":5},"max_wbgt":29.96,"valid":24},"510":{"o":{"light":0,"moderate":3,"heavy":5,"very-high":6},"max_wbgt":31.01,"valid":24},"511":{"o":{"light":0,"moderate":2,"heavy":4,"very-high":6},"max_wbgt":30.8,"valid":24},"512":{"o":{"light":0,"moderate":1,"heavy":2,"very-high":6},"max_wbgt":30.07,"valid":24},"513":{"o":{"light":0,"moderate":2,"heavy":4,"very-high":5},"max_wbgt":30.78,"valid":24},"514":{"o":{"light":0,"moderate":1,"heavy":4,"very-high":6},"max_wbgt":30.01,"valid":24},"515":{"o":{"light":0,"moderate":0,"heavy":2,"very-high":6},"max_wbgt":29.76,"valid":24},"516":{"o":{"light":0,"moderate":0,"heavy":1,"very-high":4},"max_wbgt":28.58,"valid":24},"517":{"o":{"light":0,"moderate":2,"heavy":5,"very-high":6},"max_wbgt":30.8,"valid":24},"518":{"o":{"light":0,"moderate":2,"heavy":5,"very-high":5},"max_wbgt":31.19,"valid":24},"519":{"o":{"light":0,"moderate":2,"heavy":5,"very-high":5},"max_wbgt":29.66,"valid":24},"520":{"o":{"light":0,"moderate":3,"heavy":5,"very-high":6},"max_wbgt":30.53,"valid":24},"521":{"o":{"light":0,"moderate":0,"heavy":2,"very-high":4},"max_wbgt":28.46,"valid":24},"522":{"o":{"light":0,"moderate":0,"heavy":1,"very-high":4},"max_wbgt":29.01,"valid":24},"523":{"o":{"light":0,"moderate":1,"heavy":3,"very-high":5},"max_wbgt":30.0,"valid":24},"524":{"o":{"light":0,"moderate":1,"heavy":2,"very-high":5},"max_wbgt":29.84,"valid":24},"525":{"o":{"light":0,"moderate":0,"heavy":3,"very-high":4},"max_wbgt":29.21,"valid":24},"526":{"o":{"light":0,"moderate":2,"heavy":4,"very-high":6},"max_wbgt":30.09,"valid":24},"527":{"o":{"light":0,"moderate":0,"heavy":0,"very-high":1},"max_wbgt":27.18,"valid":24},"528":{"o":{"light":0,"moderate":2,"heavy":4,"very-high":5},"max_wbgt":33.94,"valid":24},"529":{"o":{"light":0,"moderate":4,"heavy":5,"very-high":6},"max_wbgt":30.03,"valid":24},"530":{"o":{"light":0,"moderate":0,"heavy":0,"very-high":1},"max_wbgt":26.26,"valid":24},"531":{"o":{"light":0,"moderate":0,"heavy":1,"very-high":2},"max_wbgt":28.05,"valid":24},"532":{"o":{"light":0,"moderate":3,"heavy":4,"very-high":5},"max_wbgt":30.58,"valid":24},"533":{"o":{"light":0,"moderate":0,"heavy":2,"very-high":6},"max_wbgt":29.15,"valid":24},"534":{"o":{"light":0,"moderate":3,"heavy":6,"very-high":6},"max_wbgt":30.73,"valid":24},"535":{"o":{"light":0,"moderate":1,"heavy":2,"very-high":5},"max_wbgt":29.3,"valid":24},"536":{"o":{"light":0,"moderate":1,"heavy":3,"very-high":5},"max_wbgt":29.65,"valid":24},"537":{"o":{"light":0,"moderate":0,"heavy":2,"very-high":4},"max_wbgt":28.84,"valid":24},"538":{"o":{"light":0,"moderate":1,"heavy":3,"very-high":5},"max_wbgt":29.21,"valid":24},"539":{"o":{"light":0,"moderate":3,"heavy":6,"very-high":6},"max_wbgt":30.12,"valid":24},"540":{"o":{"light":0,"moderate":3,"heavy":5,"very-high":6},"max_wbgt":29.4,"valid":24},"541":{"o":{"light":1,"moderate":2,"heavy":4,"very-high":4},"max_wbgt":32.54,"valid":24},"542":{"o":{"light":0,"moderate":1,"heavy":4,"very-high":5},"max_wbgt":29.29,"valid":24},"543":{"o":{"light":0,"moderate":3,"heavy":4,"very-high":4},"max_wbgt":31.85,"valid":24},"544":{"o":{"light":0,"moderate":0,"heavy":0,"very-high":0},"max_wbgt":24.24,"valid":24},"545":{"o":{"light":1,"moderate":4,"heavy":5,"very-high":5},"max_wbgt":31.05,"valid":24},"546":{"o":{"light":1,"moderate":4,"heavy":6,"very-high":6},"max_wbgt":31.01,"valid":24},"547":{"o":{"light":1,"moderate":5,"heavy":6,"very-high":6},"max_wbgt":31.55,"valid":24},"548":{"o":{"light":0,"moderate":5,"heavy":6,"very-high":6},"max_wbgt":31.31,"valid":24},"549":{"o":{"light":0,"moderate":2,"heavy":6,"very-high":6},"max_wbgt":30.42,"valid":24},"550":{"o":{"light":0,"moderate":5,"heavy":6,"very-high":6},"max_wbgt":30.98,"valid":24},"551":{"o":{"light":0,"moderate":2,"heavy":5,"very-high":6},"max_wbgt":30.52,"valid":24},"552":{"o":{"light":0,"moderate":2,"heavy":4,"very-high":6},"max_wbgt":29.97,"valid":24},"553":{"o":{"light":0,"moderate":1,"heavy":2,"very-high":5},"max_wbgt":28.6,"valid":24},"554":{"o":{"light":0,"moderate":1,"heavy":3,"very-high":4},"max_wbgt":29.48,"valid":24},"555":{"o":{"light":0,"moderate":1,"heavy":2,"very-high":4},"max_wbgt":28.83,"valid":24},"556":{"o":{"light":0,"moderate":1,"heavy":2,"very-high":5},"max_wbgt":29.1,"valid":24},"557":{"o":{"light":0,"moderate":1,"heavy":2,"very-high":4},"max_wbgt":29.22,"valid":24},"558":{"o":{"light":0,"moderate":1,"heavy":2,"very-high":5},"max_wbgt":29.69,"valid":24},"559":{"o":{"light":0,"moderate":1,"heavy":2,"very-high":4},"max_wbgt":30.02,"valid":24},"560":{"o":{"light":0,"moderate":0,"heavy":2,"very-high":2},"max_wbgt":28.7,"valid":24},"561":{"o":{"light":0,"moderate":0,"heavy":2,"very-high":4},"max_wbgt":28.51,"valid":24},"562":{"o":{"light":0,"moderate":0,"heavy":1,"very-high":2},"max_wbgt":28.13,"valid":24},"563":{"o":{"light":0,"moderate":0,"heavy":2,"very-high":4},"max_wbgt":27.7,"valid":24},"564":{"o":{"light":0,"moderate":0,"heavy":1,"very-high":2},"max_wbgt":28.08,"valid":24},"565":{"o":{"light":0,"moderate":1,"heavy":2,"very-high":4},"max_wbgt":29.0,"valid":24},"566":{"o":{"light":0,"moderate":0,"heavy":1,"very-high":2},"max_wbgt":28.07,"valid":24},"567":{"o":{"light":0,"moderate":0,"heavy":1,"very-high":2},"max_wbgt":28.4,"valid":24},"568":{"o":{"light":0,"moderate":0,"heavy":0,"very-high":2},"max_wbgt":26.58,"valid":24},"569":{"o":{"light":2,"moderate":5,"heavy":6,"very-high":6},"max_wbgt":30.6,"valid":24},"570":{"o":{"light":0,"moderate":0,"heavy":0,"very-high":0},"max_wbgt":25.51,"valid":24},"571":{"o":{"light":0,"moderate":0,"heavy":1,"very-high":2},"max_wbgt":26.57,"valid":24},"572":{"o":{"light":0,"moderate":0,"heavy":0,"very-high":1},"max_wbgt":26.49,"valid":24},"573":{"o":{"light":0,"moderate":0,"heavy":1,"very-high":2},"max_wbgt":26.72,"valid":24},"574":{"o":{"light":0,"moderate":0,"heavy":0,"very-high":1},"max_wbgt":25.36,"valid":24},"575":{"o":{"light":0,"moderate":2,"heavy":5,"very-high":6},"max_wbgt":30.13,"valid":24},"576":{"o":{"light":0,"moderate":0,"heavy":0,"very-high":0},"max_wbgt":25.11,"valid":24},"577":{"o":{"light":0,"moderate":0,"heavy":1,"very-high":2},"max_wbgt":26.68,"valid":24},"578":{"o":{"light":0,"moderate":0,"heavy":1,"very-high":2},"max_wbgt":27.32,"valid":24},"579":{"o":{"light":0,"moderate":0,"heavy":2,"very-high":6},"max_wbgt":29.96,"valid":24},"580":{"o":{"light":0,"moderate":0,"heavy":3,"very-high":4},"max_wbgt":30.32,"valid":24},"581":{"o":{"light":0,"moderate":0,"heavy":0,"very-high":1},"max_wbgt":26.77,"valid":24},"582":{"o":{"light":0,"moderate":0,"heavy":0,"very-high":1},"max_wbgt":25.97,"valid":24},"583":{"o":{"light":0,"moderate":0,"heavy":0,"very-high":1},"max_wbgt":25.86,"valid":24},"584":{"o":{"light":0,"moderate":0,"heavy":1,"very-high":2},"max_wbgt":27.69,"valid":24},"585":{"o":{"light":1,"moderate":3,"heavy":5,"very-high":6},"max_wbgt":30.63,"valid":24},"586":{"o":{"light":1,"moderate":4,"heavy":5,"very-high":6},"max_wbgt":30.62,"valid":24},"587":{"o":{"light":0,"moderate":5,"heavy":6,"very-high":6},"max_wbgt":28.94,"valid":24},"588":{"o":{"light":0,"moderate":4,"heavy":5,"very-high":6},"max_wbgt":30.14,"valid":24},"589":{"o":{"light":0,"moderate":4,"heavy":4,"very-high":5},"max_wbgt":30.46,"valid":24},"590":{"o":{"light":0,"moderate":0,"heavy":2,"very-high":2},"max_wbgt":27.04,"valid":24},"591":{"o":{"light":1,"moderate":4,"heavy":5,"very-high":5},"max_wbgt":30.55,"valid":24},"592":{"o":{"light":0,"moderate":3,"heavy":5,"very-high":6},"max_wbgt":29.75,"valid":24},"593":{"o":{"light":0,"moderate":2,"heavy":5,"very-high":6},"max_wbgt":29.77,"valid":24},"594":{"o":{"light":1,"moderate":3,"heavy":5,"very-high":6},"max_wbgt":31.08,"valid":24},"595":{"o":{"light":1,"moderate":5,"heavy":6,"very-high":6},"max_wbgt":31.25,"valid":24},"596":{"o":{"light":0,"moderate":0,"heavy":0,"very-high":3},"max_wbgt":27.09,"valid":24},"597":{"o":{"light":0,"moderate":5,"heavy":6,"very-high":6},"max_wbgt":30.0,"valid":24},"598":{"o":{"light":0,"moderate":5,"heavy":6,"very-high":6},"max_wbgt":29.91,"valid":24},"599":{"o":{"light":0,"moderate":0,"heavy":1,"very-high":2},"max_wbgt":27.47,"valid":24},"600":{"o":{"light":0,"moderate":2,"heavy":5,"very-high":6},"max_wbgt":29.64,"valid":24},"601":{"o":{"light":0,"moderate":2,"heavy":5,"very-high":6},"max_wbgt":29.32,"valid":24},"602":{"o":{"light":1,"moderate":5,"heavy":6,"very-high":6},"max_wbgt":32.3,"valid":24},"603":{"o":{"light":1,"moderate":6,"heavy":6,"very-high":6},"max_wbgt":31.63,"valid":24},"604":{"o":{"light":1,"moderate":5,"heavy":6,"very-high":6},"max_wbgt":31.31,"valid":24},"605":{"o":{"light":0,"moderate":2,"heavy":2,"very-high":5},"max_wbgt":29.63,"valid":24},"606":{"o":{"light":1,"moderate":4,"heavy":6,"very-high":6},"max_wbgt":30.63,"valid":24},"607":{"o":{"light":1,"moderate":5,"heavy":6,"very-high":6},"max_wbgt":31.13,"valid":24},"608":{"o":{"light":0,"moderate":2,"heavy":6,"very-high":6},"max_wbgt":30.46,"valid":24},"609":{"o":{"light":1,"moderate":5,"heavy":6,"very-high":6},"max_wbgt":33.12,"valid":24},"610":{"o":{"light":0,"moderate":4,"heavy":5,"very-high":6},"max_wbgt":30.44,"valid":24},"611":{"o":{"light":0,"moderate":0,"heavy":0,"very-high":0},"max_wbgt":22.01,"valid":24},"612":{"o":{"light":0,"moderate":2,"heavy":5,"very-high":6},"max_wbgt":30.15,"valid":24},"613":{"o":{"light":0,"moderate":2,"heavy":4,"very-high":6},"max_wbgt":30.11,"valid":24},"614":{"o":{"light":0,"moderate":3,"heavy":6,"very-high":6},"max_wbgt":30.7,"valid":24},"615":{"o":{"light":2,"moderate":5,"heavy":6,"very-high":6},"max_wbgt":34.27,"valid":24},"616":{"o":{"light":1,"moderate":5,"heavy":6,"very-high":6},"max_wbgt":32.01,"valid":24},"617":{"o":{"light":1,"moderate":5,"heavy":6,"very-high":6},"max_wbgt":31.86,"valid":24},"618":{"o":{"light":1,"moderate":5,"heavy":6,"very-high":6},"max_wbgt":31.96,"valid":24},"619":{"o":{"light":0,"moderate":4,"heavy":6,"very-high":6},"max_wbgt":31.43,"valid":24},"620":{"o":{"light":0,"moderate":3,"heavy":6,"very-high":6},"max_wbgt":31.07,"valid":24},"621":{"o":{"light":1,"moderate":5,"heavy":6,"very-high":6},"max_wbgt":32.23,"valid":24},"622":{"o":{"light":4,"moderate":5,"heavy":6,"very-high":6},"max_wbgt":36.57,"valid":24},"623":{"o":{"light":0,"moderate":1,"heavy":3,"very-high":6},"max_wbgt":31.47,"valid":24},"624":{"o":{"light":0,"moderate":1,"heavy":3,"very-high":6},"max_wbgt":29.79,"valid":24},"625":{"o":{"light":1,"moderate":5,"heavy":6,"very-high":6},"max_wbgt":33.81,"valid":24},"626":{"o":{"light":1,"moderate":5,"heavy":6,"very-high":6},"max_wbgt":35.65,"valid":24},"627":{"o":{"light":0,"moderate":2,"heavy":6,"very-high":6},"max_wbgt":30.57,"valid":24},"628":{"o":{"light":1,"moderate":4,"heavy":6,"very-high":6},"max_wbgt":31.0,"valid":24},"629":{"o":{"light":0,"moderate":1,"heavy":4,"very-high":6},"max_wbgt":28.74,"valid":24},"630":{"o":{"light":0,"moderate":0,"heavy":2,"very-high":4},"max_wbgt":28.56,"valid":24},"631":{"o":{"light":0,"moderate":0,"heavy":1,"very-high":2},"max_wbgt":28.32,"valid":24},"632":{"o":{"light":0,"moderate":0,"heavy":2,"very-high":5},"max_wbgt":28.5,"valid":24},"633":{"o":{"light":0,"moderate":2,"heavy":3,"very-high":5},"max_wbgt":29.46,"valid":24},"634":{"o":{"light":1,"moderate":6,"heavy":6,"very-high":6},"max_wbgt":31.48,"valid":24},"635":{"o":{"light":0,"moderate":6,"heavy":6,"very-high":6},"max_wbgt":32.73,"valid":24},"636":{"o":{"light":3,"moderate":4,"heavy":5,"very-high":6},"max_wbgt":31.91,"valid":24},"637":{"o":{"light":1,"moderate":6,"heavy":6,"very-high":6},"max_wbgt":31.78,"valid":24},"638":{"o":{"light":0,"moderate":5,"heavy":5,"very-high":6},"max_wbgt":30.44,"valid":24},"639":{"o":{"light":0,"moderate":5,"heavy":6,"very-high":6},"max_wbgt":30.07,"valid":24},"640":{"o":{"light":0,"moderate":3,"heavy":5,"very-high":6},"max_wbgt":29.38,"valid":24}}}